mimcvdf/__init__.py
mimcvdf/mimc.py
mimcvdf-1.1.0.dist-info/LICENSE
mimcvdf-1.1.0.dist-info/METADATA
mimcvdf-1.1.0.dist-info/WHEEL
mimcvdf-1.1.0.dist-info/top_level.txt
mimcvdf-1.1.0.dist-info/RECORD
