Metadata-Version: 2.1
Name: mimcvdf
Version: 1.1.0
Summary: Generic high level VDF using MiMC
Home-page: https://www.chaoswebs.net/
Author: Kevin Froman
Author-email: beardog@mailbox.org
License: UNKNOWN
Platform: UNKNOWN
Classifier: Programming Language :: Python :: 3
Classifier: License :: OSI Approved :: GNU General Public License v3 (GPLv3)
Classifier: Operating System :: OS Independent
